[
  {
    "id": "VFML-ML-2026-001",
    "name": "Aarav Sharma",
    "track": "Machine Learning",
    "status": "Completed",
    "issueDate": "2026-02-15",
    "lorStatus": "Issued"
  },
  {
    "id": "VFML-ML-2026-002",
    "name": "Priya Patel",
    "track": "Machine Learning",
    "status": "Completed",
    "issueDate": "2026-02-20",
    "lorStatus": "Pending Review"
  },
  {
    "id": "VFML-DA-2026-001",
    "name": "Rahul Verma",
    "track": "Data Analysis",
    "status": "Completed",
    "issueDate": "2026-01-28",
    "lorStatus": "Issued"
  },
  {
    "id": "VFML-DA-2026-002",
    "name": "Sneha Iyer",
    "track": "Data Analysis",
    "status": "Completed",
    "issueDate": "2026-02-10",
    "lorStatus": "Not Eligible"
  },
  {
    "id": "VFML-ML-2026-003",
    "name": "Arjun Reddy",
    "track": "Machine Learning",
    "status": "In Progress",
    "issueDate": "—",
    "lorStatus": "N/A"
  }
]
